divemathjax3/__init__.py
divemathjax3/_version.py
divemathjax3/labextension/package.json
divemathjax3/labextension/static/1cb1c39ea642f26a4dfed230b4aea1c3c218689421f6e9c0a7c1811693c4fa07.woff
divemathjax3/labextension/static/32792104b5ef69eded905b6d1598ed05d8087684d38e7a94d52e3c38ba16f47e.woff
divemathjax3/labextension/static/355254db9ca10a09a3b5f0929d74eb4670f44fbe864c07526a06213e0a0caf6c.woff
divemathjax3/labextension/static/3de784d07b9fa8f104c10928a878ee879cf3305cae5195cba663c9c2bb0195eb.woff
divemathjax3/labextension/static/568.81911e5f6a9bb1ec0969.js
divemathjax3/labextension/static/648.6618d3c510dee20542be.js
divemathjax3/labextension/static/721921bab0d001ebff0206c24cb5de6ca136467bf1843a7aa32030ba061d1e92.woff
divemathjax3/labextension/static/747.d50ca2bec8ccc448ab5e.js
divemathjax3/labextension/static/869.69e78d31de7004f1cd75.js
divemathjax3/labextension/static/869.69e78d31de7004f1cd75.js.LICENSE.txt
divemathjax3/labextension/static/870673df72e70f87c91a5a317d558c2c3b54392264ad79bbadc6d424ae8765fe.woff
divemathjax3/labextension/static/88b98cad3688915e50da55553ff6ad185e0dce134b47f176e91b100f8a9b175c.woff
divemathjax3/labextension/static/8ea8dbb1b02e6f730f55b4cb5d413b785b9f5c39807d0a0fa7da206a0824a457.woff
divemathjax3/labextension/static/a009bea404f7a500ded48f8b9ad9cf16e12504b3195dd9e25975289b8256b0f0.woff
divemathjax3/labextension/static/af96f67d7accf5fd2a4a682d0b9f8b339f8ea6fe34c310c1694c8ba7f6ddc96f.woff
divemathjax3/labextension/static/b418136e3b384baaadecb70bd3c48a8da9825210130b2897db808c44efc883cb.woff
divemathjax3/labextension/static/c56da8d69f1a0208b8e0703656c3264b6dd748bd452524c82b0385b60f6a68c1.woff
divemathjax3/labextension/static/fc6ddf5df402b263cfb158aed8e89972542c34b719cd87b1db30461985f7bd5b.woff
divemathjax3/labextension/static/remoteEntry.e6bd1eec9b5a4a6a3151.js
divemathjax3/labextension/static/style.js
divemathjax3/labextension/static/third-party-licenses.json
divemathjax3-0.0.2.data/data/share/jupyter/labextensions/divemathjax3/install.json
divemathjax3-0.0.2.dist-info/METADATA
divemathjax3-0.0.2.dist-info/WHEEL
divemathjax3-0.0.2.dist-info/top_level.txt
divemathjax3-0.0.2.dist-info/RECORD
