Metadata-Version: 2.1
Name: divemathjax3
Version: 0.0.2
Summary: MathJax 3 math renderer for DIVE.
Home-page: https://github.com/dive4dec/divemathjax3
Author: DIVE
Author-email: chungc@alum.mit.edu
License: BSD-3-Clause
Platform: Linux
Platform: Mac OS X
Platform: Windows
Classifier: Intended Audience :: Education
Classifier: Intended Audience :: Developers
Classifier: Intended Audience :: Science/Research
Classifier: License :: OSI Approved :: BSD License
Classifier: Framework :: Jupyter
Classifier: Framework :: Jupyter :: JupyterLab
Classifier: Framework :: Jupyter :: JupyterLab :: 3
Classifier: Programming Language :: Python
Classifier: Programming Language :: Python :: 3.6
Classifier: Programming Language :: Python :: 3.7
Classifier: Programming Language :: Python :: 3.8
Classifier: Programming Language :: Python :: 3.9
Classifier: Programming Language :: Python :: 3.10
Classifier: Framework :: Jupyter
Requires-Python: >=3.6
